{"retHeader":{"totalput":33},"retcode":"cbd","retmsg":1,"reqdata":[{"cbd_id":"200705","CityID":"2007","CBD_Name":"\u957f\u5b89\u9547","hotelnum":"25"},{"cbd_id":"200701","CityID":"2007","CBD_Name":"\u539a\u8857\u9547","hotelnum":"23"},{"cbd_id":"200713","CityID":"2007","CBD_Name":"\u5357\u57ce","hotelnum":"22"},{"cbd_id":"200703","CityID":"2007","CBD_Name":"\u864e\u95e8\u9547","hotelnum":"21"},{"cbd_id":"200707","CityID":"2007","CBD_Name":"\u5e38\u5e73\u9547","hotelnum":"20"},{"cbd_id":"200702","CityID":"2007","CBD_Name":"\u839e\u57ce","hotelnum":"16"},{"cbd_id":"200712","CityID":"2007","CBD_Name":"\u4e1c\u57ce","hotelnum":"12"},{"cbd_id":"200716","CityID":"2007","CBD_Name":"\u4e07\u6c5f\u9547","hotelnum":"7"},{"cbd_id":"200706","CityID":"2007","CBD_Name":"\u9ec4\u6c5f\u9547","hotelnum":"6"},{"cbd_id":"200708","CityID":"2007","CBD_Name":"\u5858\u53a6\u9547","hotelnum":"6"},{"cbd_id":"200709","CityID":"2007","CBD_Name":"\u5bee\u6b65\u9547","hotelnum":"6"},{"cbd_id":"200718","CityID":"2007","CBD_Name":"\u5927\u6717\u9547","hotelnum":"6"},{"cbd_id":"200719","CityID":"2007","CBD_Name":"\u77f3\u78a3\u9547","hotelnum":"6"},{"cbd_id":"200721","CityID":"2007","CBD_Name":"\u6e05\u6eaa\u9547","hotelnum":"6"},{"cbd_id":"200704","CityID":"2007","CBD_Name":"\u6a1f\u6728\u5934\u9547","hotelnum":"5"},{"cbd_id":"200711","CityID":"2007","CBD_Name":"\u51e4\u5c97\u9547","hotelnum":"4"},{"cbd_id":"200723","CityID":"2007","CBD_Name":"\u4e1c\u5751\u9547","hotelnum":"4"},{"cbd_id":"200714","CityID":"2007","CBD_Name":"\u8336\u5c71\u9547","hotelnum":"3"},{"cbd_id":"200720","CityID":"2007","CBD_Name":"\u6865\u5934\u9547","hotelnum":"3"},{"cbd_id":"200728","CityID":"2007","CBD_Name":"\u6a2a\u6ca5\u9547","hotelnum":"3"},{"cbd_id":"200710","CityID":"2007","CBD_Name":"\u77f3\u9f99\u9547","hotelnum":"2"},{"cbd_id":"200722","CityID":"2007","CBD_Name":"\u4f01\u77f3\u9547","hotelnum":"2"},{"cbd_id":"200725","CityID":"2007","CBD_Name":"\u9ad8\u57d7\u9547","hotelnum":"2"},{"cbd_id":"200726","CityID":"2007","CBD_Name":"\u4e2d\u5802\u9547","hotelnum":"2"},{"cbd_id":"200730","CityID":"2007","CBD_Name":"\u9ebb\u6d8c\u9547","hotelnum":"2"},{"cbd_id":"200715","CityID":"2007","CBD_Name":"\u77f3\u6392\u9547","hotelnum":"1"},{"cbd_id":"200717","CityID":"2007","CBD_Name":"\u5927\u5cad\u5c71\u9547","hotelnum":"1"},{"cbd_id":"200724","CityID":"2007","CBD_Name":"\u6d2a\u6885\u9547","hotelnum":"1"},{"cbd_id":"200727","CityID":"2007","CBD_Name":"\u6c99\u7530\u9547","hotelnum":"1"},{"cbd_id":"200729","CityID":"2007","CBD_Name":"\u8c22\u5c97\u9547","hotelnum":"1"},{"cbd_id":"200731","CityID":"2007","CBD_Name":"\u671b\u725b\u58a9\u9547","hotelnum":"1"},{"cbd_id":"200732","CityID":"2007","CBD_Name":"\u677e\u5c71\u6e56\u56ed\u533a","hotelnum":"0"},{"cbd_id":"200733","CityID":"2007","CBD_Name":"\u9053\u6ed8\u9547","hotelnum":"0"}]}