<?xml version="1.0" encoding="utf-8" ?>
<dwsync>
<file name="i_f_01.gif" server="w91.126t.net" local="130192151400000000" remote="130223572800000000" />
<file name="i_f_02.gif" server="w91.126t.net" local="130192151400000000" remote="130223572800000000" />
<file name="i_f_03.gif" server="w91.126t.net" local="130192151400000000" remote="130223572800000000" />
<file name="i_f_04.gif" server="w91.126t.net" local="130192151400000000" remote="130223572800000000" />
<file name="i_f_05.gif" server="w91.126t.net" local="130192151400000000" remote="130223572800000000" />
<file name="i_f_06.gif" server="w91.126t.net" local="130192151400000000" remote="130223572800000000" />
<file name="i_f_07.gif" server="w91.126t.net" local="130192151400000000" remote="130223572800000000" />
<file name="i_f_08.gif" server="w91.126t.net" local="130192151400000000" remote="130223572800000000" />
<file name="i_f_09.gif" server="w91.126t.net" local="130192151400000000" remote="130223572800000000" />
<file name="i_f_10.gif" server="w91.126t.net" local="130192151400000000" remote="130223572800000000" />
<file name="i_f_11.gif" server="w91.126t.net" local="130192151400000000" remote="130223572800000000" />
<file name="i_f_12.gif" server="w91.126t.net" local="130192151400000000" remote="130223572800000000" />
<file name="i_f_13.gif" server="w91.126t.net" local="130192151400000000" remote="130223572800000000" />
<file name="i_f_14.gif" server="w91.126t.net" local="130192151400000000" remote="130223572800000000" />
<file name="i_f_15.gif" server="w91.126t.net" local="130192151400000000" remote="130223572800000000" />
<file name="i_f_16.gif" server="w91.126t.net" local="130192151400000000" remote="130223572800000000" />
<file name="i_f_17.gif" server="w91.126t.net" local="130192151400000000" remote="130223572800000000" />
<file name="i_f_18.gif" server="w91.126t.net" local="130192151400000000" remote="130223572800000000" />
<file name="i_f_19.gif" server="w91.126t.net" local="130192151400000000" remote="130223572800000000" />
<file name="i_f_20.gif" server="w91.126t.net" local="130192151400000000" remote="130223572800000000" />
<file name="i_f_21.gif" server="w91.126t.net" local="130192151400000000" remote="130223572800000000" />
<file name="i_f_22.gif" server="w91.126t.net" local="130192151400000000" remote="130223572800000000" />
<file name="i_f_23.gif" server="w91.126t.net" local="130192151400000000" remote="130223572800000000" />
<file name="i_f_24.gif" server="w91.126t.net" local="130192151400000000" remote="130223572800000000" />
<file name="i_f_25.gif" server="w91.126t.net" local="130192151400000000" remote="130223572800000000" />
<file name="i_f_26.gif" server="w91.126t.net" local="130192151400000000" remote="130223572800000000" />
<file name="i_f_27.gif" server="w91.126t.net" local="130192151400000000" remote="130223572800000000" />
<file name="i_f_28.gif" server="w91.126t.net" local="130192151400000000" remote="130223572800000000" />
<file name="i_f_29.gif" server="w91.126t.net" local="130192151400000000" remote="130223572800000000" />
<file name="i_f_30.gif" server="w91.126t.net" local="130192151400000000" remote="130223572800000000" />
<file name="i_f_31.gif" server="w91.126t.net" local="130192151400000000" remote="130223572800000000" />
<file name="i_f_32.gif" server="w91.126t.net" local="130192151400000000" remote="130223573400000000" />
<file name="i_f_33.gif" server="w91.126t.net" local="130192151400000000" remote="130223573400000000" />
<file name="i_f_34.gif" server="w91.126t.net" local="130192151400000000" remote="130223573400000000" />
<file name="i_f_35.gif" server="w91.126t.net" local="130192151400000000" remote="130223573400000000" />
<file name="i_f_36.gif" server="w91.126t.net" local="130192151400000000" remote="130223573400000000" />
<file name="i_f_37.gif" server="w91.126t.net" local="130192151400000000" remote="130223573400000000" />
<file name="i_f_38.gif" server="w91.126t.net" local="130192151400000000" remote="130223573400000000" />
<file name="i_f_39.gif" server="w91.126t.net" local="130192151400000000" remote="130223573400000000" />
<file name="i_f_40.gif" server="w91.126t.net" local="130192151400000000" remote="130223573400000000" />
<file name="i_f_41.gif" server="w91.126t.net" local="130192151400000000" remote="130223573400000000" />
<file name="i_f_42.gif" server="w91.126t.net" local="130192151400000000" remote="130223573400000000" />
<file name="i_f_43.gif" server="w91.126t.net" local="130192151400000000" remote="130223573400000000" />
<file name="i_f_44.gif" server="w91.126t.net" local="130192151400000000" remote="130223573400000000" />
<file name="i_f_45.gif" server="w91.126t.net" local="130192151400000000" remote="130223573400000000" />
<file name="i_f_46.gif" server="w91.126t.net" local="130192151400000000" remote="130223573400000000" />
<file name="i_f_47.gif" server="w91.126t.net" local="130192151400000000" remote="130223573400000000" />
<file name="i_f_48.gif" server="w91.126t.net" local="130192151400000000" remote="130223573400000000" />
<file name="i_f_49.gif" server="w91.126t.net" local="130192151400000000" remote="130223573400000000" />
<file name="i_f_50.gif" server="w91.126t.net" local="130192151400000000" remote="130223573400000000" />
</dwsync>