{"retHeader":{"totalput":14,"totalpg":2,"pagesize":10,"page":1},"retcode":"search","retmsg":1,"reqdata":[{"HotelName":"\u4e09\u660e\u4e39\u5fb7\u516c\u8def\u5bbe\u9986","min_jiage":88,"esdid":"141005","ID":116396,"cbd":null,"Address":"\u4e09\u5143\u533a\u5bcc\u5174\u8def13\u53f7\uff08\u5e02\u516c\u8def\u5c40\u5927\u9662\uff09","Picture":"http:\/\/tp1.znimg.com\/images\/nophoto_1.gif","xingji":0,"df_haoping":"0$0$0","esdname":""},{"HotelName":"\u4e09\u660e\u6c90\u9038\u57ce\u5e02\u9152\u5e97\uff08\u539f\u4e09\u660e\u9999\u820d\u4e3d\u90fd\u9152\u5e97\uff09","min_jiage":188,"esdid":"141005","ID":115446,"cbd":null,"Address":"\u4e09\u5143\u533a\u65b0\u5e02\u5357\u8def313\u53f7\uff08\u57fa\u7763\u6559\u5802\u5bf9\u9762\uff09","Picture":"http:\/\/tp1.znimg.com\/Hotel_Images\/115446\/160x120_215257bb-add0-4176-8da2-93da67077425.jpg","xingji":6,"df_haoping":"0$0$0","esdname":""},{"HotelName":"\u4e09\u660e\u5112\u5bb6\u5bbe\u9986","min_jiage":80,"esdid":"141005","ID":115060,"cbd":null,"Address":"\u4e09\u5143\u533a\u8346\u4e1c205\u56fd\u9053\u65c1\uff08\u4e09\u660e\u5b66\u9662\u5357\u5927\u95e8\u5bf9\u9762\uff09","Picture":"http:\/\/tp1.znimg.com\/images\/nophoto_1.gif","xingji":0,"df_haoping":"0$0$0","esdname":""},{"HotelName":"\u4e09\u660e\u4eac\u4e1c\u5546\u52a1\u5bbe\u9986","min_jiage":80,"esdid":"141005","ID":114848,"cbd":null,"Address":"\u4e09\u5143\u533a\u8346\u4e1c\u67514\u53f7\uff08\u4e09\u660e\u5b66\u9662\u5357\u95e8\u5bf9\u9762\uff09","Picture":"http:\/\/tp1.znimg.com\/Hotel_Images\/114848\/160x120_a0cf6c67-c32f-4d56-a69a-c71aa81efccd.jpg","xingji":0,"df_haoping":"0$0$0","esdname":""},{"HotelName":"\u4e09\u660e\u7687\u5ef7\u4e3d\u666f\u9152\u5e97","min_jiage":316,"esdid":" ","ID":113853,"cbd":null,"Address":"\u6885\u5217\u533a\u4e7e\u9f99\u65b0\u6751362\u5e62","Picture":"http:\/\/tp1.znimg.com\/Hotel_Images\/113853\/160x120_0a4ec830-c03d-4bcb-bbf5-9c6ec621213a.jpg","xingji":4,"df_haoping":"1$0$0","esdname":""},{"HotelName":"\u4e09\u660e\u91d1\u60a6\u5546\u52a1\u5bbe\u9986","min_jiage":158,"esdid":"141001","ID":112170,"cbd":null,"Address":"\u6885\u5217\u533a\u5f90\u78a7\u4e8c\u675147\u5e62\uff08\u6c83\u5c14\u739b\u8d85\u5e02\u5bf9\u9762\uff09","Picture":"http:\/\/tp1.znimg.com\/Hotel_Images\/112170\/160x120_6d198e3c-7b0f-439e-87c8-51f20a1eb461.jpg","xingji":0,"df_haoping":"0$0$0","esdname":""},{"HotelName":"\u4e09\u660e\u5409\u4e3d\u5546\u52a1\u9152\u5e97","min_jiage":169,"esdid":"141001","ID":110528,"cbd":null,"Address":"\u4e7e\u9f99\u65b0\u6751201\u5e62\uff08\u9ad8\u901f\u4ea4\u8b66\u652f\u961f\u65c1\uff09","Picture":"http:\/\/tp1.znimg.com\/Hotel_Images\/110528\/160x120_2250a466-6fc7-4db5-a7cb-e1dba32f8105.jpg","xingji":0,"df_haoping":"2$0$0","esdname":""},{"HotelName":"\u4e09\u660e\u6885\u56ed\u56fd\u9645\u5927\u9152\u5e97","min_jiage":360,"esdid":"141001","ID":107814,"cbd":null,"Address":"\u4e1c\u65b0\u4e94\u8def\u5f90\u78a7\u65b0\u57ce\uff08\u6c83\u5c14\u739b\u8d2d\u7269\u5e7f\u573a\u5bf9\u9762\uff09","Picture":"http:\/\/tp1.znimg.com\/Hotel_Images\/107814\/160x120_20130228b3259e264fe50384e509430ab29ec9d4.jpg","xingji":2,"df_haoping":"9$0$0","esdname":""},{"HotelName":"\u4e09\u660e\u683c\u6797\u8c6a\u6cf0\uff08\u6c7d\u8f66\u897f\u5ba2\u7ad9\u5feb\u6377\u9152\u5e97\uff09","min_jiage":132,"esdid":" ","ID":107535,"cbd":null,"Address":"\u4e09\u660e\u5e02\u4e09\u5143\u533a\u957f\u5b89\u8def17\u53f7\u660e\u6d77\u946b\u94a2\u6750\u5e02\u573a5\u5e62\u5546\u52a1\u697c\uff08\u7ea2\u661f\u7f8e\u51ef\u9f99\u65c1\uff09","Picture":"http:\/\/tp1.znimg.com\/Hotel_Images\/107535\/160x120_20130221c9f0f895fb98ab9159f51fd0297e236d.jpg","xingji":6,"df_haoping":"0$0$0","esdname":""},{"HotelName":"\u4e09\u660e\u9e92\u9e9f\u5c71\u82b1\u56ed\u9152\u5e97","min_jiage":198,"esdid":"141001","ID":107093,"cbd":null,"Address":"\u6885\u5217\u533a\u9e92\u9e9f\u5c71\u516c\u56ed\u5165\u53e3\u5904\u5357\u4fa7\uff08\u5730\u5904\u9e92\u9e9f\u5c71\u666f\u533a\u5185\uff09","Picture":"http:\/\/tp1.znimg.com\/Hotel_Images\/107093\/160x120_47b9b1d9-cd33-4aa6-8bb4-e3e826a7b7a1.jpg","xingji":0,"df_haoping":"15$0$0","esdname":""}]}